{
    "code":1,
    "message":"OK",
    "result":{
        "0xe070cca5cdfb3f2b434fb91eaf67fa2084f324d7":{
            "buy_tax":"0.01",
            "can_take_back_ownership":"0",
            "cannot_buy":"0",
            "cannot_sell_all":"0",
            "creator_address":"0x69db4585b7ae87fad64064584349971609e73772",
            "creator_balance":"7574.83910116734480349",
            "creator_percent":"0.00074",
            "dex":[
                {
                    "name":"PancakeV2",
                    "liquidity":"453382.36175605",
                    "pair":"0xe94A77CbCC0590B0738C48B2594c08e456feD89D"
                },
                {
                    "name":"PancakeV2",
                    "liquidity":"32.52500085",
                    "pair":"0x2E126FDdAa1076E46fd50450A8597acC28D599E7"
                },
                {
                    "name":"PancakeV2",
                    "liquidity":"0.78538662",
                    "pair":"0x4AE80E10CEeE19550228D4c6dA226D0D81976b3D"
                },
                {
                    "name":"PancakeV2",
                    "liquidity":"0.08913291",
                    "pair":"0x5617c8A9F7fF6A657FC65a62Ae1894D294878B22"
                },
                {
                    "name":"FstSwap",
                    "liquidity":"0.00000013",
                    "pair":"0x08201a70E3Ed5EAF4795CC1576371172Ec8af52f"
                }
            ],
            "external_call":"0",
            "hidden_owner":"0",
            "holder_count":"8900",
            "holders":[
                {
                    "address":"0xe94a77cbcc0590b0738c48b2594c08e456fed89d",
                    "tag":"PancakeV2",
                    "is_contract":1,
                    "balance":"3507941.2958683",
                    "percent":"0.342572392174638671",
                    "is_locked":0
                },
                {
                    "address":"0x000000000000000000000000000000000000dead",
                    "tag":"",
                    "is_contract":0,
                    "balance":"1651062.0134249",
                    "percent":"0.161236524748525390",
                    "is_locked":1
                },
                {
                    "address":"0x407993575c91ce7643a4d4ccacc9a98c36ee1bbe",
                    "tag":"PinkLock02",
                    "is_contract":1,
                    "balance":"614400",
                    "percent":"0.060000000000000000",
                    "is_locked":1,
                    "locked_detail":[
                        {
                            "amount":"614400.000000000000000000",
                            "end_time":"2023-02-16T14:00:00+00:00",
                            "opt_time":"2022-08-18T06:23:46+00:00"
                        }
                    ]
                },
                {
                    "address":"0xfd74aaa2bfb21e59e911481cb8f6ab6f3aaad1d6",
                    "tag":"",
                    "is_contract":0,
                    "balance":"85278.740680839",
                    "percent":"0.008328002019613183",
                    "is_locked":0
                },
                {
                    "address":"0x34692e4288bb4cbecb0f442330e1150ee9110902",
                    "tag":"",
                    "is_contract":0,
                    "balance":"83159.74150167",
                    "percent":"0.008121068506022460",
                    "is_locked":0
                },
                {
                    "address":"0x89312ace5c29e72feae56359d740df12019ddf05",
                    "tag":"",
                    "is_contract":0,
                    "balance":"74907.411368183",
                    "percent":"0.007315176891424121",
                    "is_locked":0
                },
                {
                    "address":"0xd57407d79f2b1c9e1dcbcaac00a3e183043bc545",
                    "tag":"",
                    "is_contract":0,
                    "balance":"71869.384631279",
                    "percent":"0.007018494592898339",
                    "is_locked":0
                },
                {
                    "address":"0x76f5b229c060252b6e0113bf93c8608b380a1337",
                    "tag":"",
                    "is_contract":0,
                    "balance":"65808.800292641",
                    "percent":"0.006426640653578222",
                    "is_locked":0
                },
                {
                    "address":"0x5d9d66c009ae5d62f77af25a4ee622a5b415b1c2",
                    "tag":"",
                    "is_contract":0,
                    "balance":"65074.47",
                    "percent":"0.006354928710937500",
                    "is_locked":0
                },
                {
                    "address":"0x0c3bc812520610d93d1dad293c272a3d3171b8b8",
                    "tag":"",
                    "is_contract":0,
                    "balance":"62356.155892829",
                    "percent":"0.006089468348909082",
                    "is_locked":0
                }
            ],
            "is_anti_whale":"0",
            "is_blacklisted":"0",
            "is_honeypot":"0",
            "is_in_dex":"1",
            "is_mintable":"0",
            "is_open_source":"1",
            "is_proxy":"0",
            "is_whitelisted":"0",
            "lp_holder_count":"18",
            "lp_holders":[
                {
                    "address":"0x000000000000000000000000000000000000dead",
                    "tag":"",
                    "is_contract":0,
                    "balance":"1080671.7910633",
                    "percent":"0.917748082125629777",
                    "is_locked":1
                },
                {
                    "address":"0x64a7b32bd4baa59bf1eff3236910f5cd5a60fa28",
                    "tag":"",
                    "is_contract":1,
                    "balance":"95057.98196039",
                    "percent":"0.080726897246983495",
                    "is_locked":0
                },
                {
                    "address":"0x416755693dd905a5b7199c5d9334ba8340e12e30",
                    "tag":"",
                    "is_contract":0,
                    "balance":"1000.1087363155",
                    "percent":"0.000849330835005458",
                    "is_locked":0
                },
                {
                    "address":"0xf88f70b3ff882dae0e83457e72d55f24232b99a6",
                    "tag":"",
                    "is_contract":0,
                    "balance":"364.01968545713",
                    "percent":"0.000309139528714400",
                    "is_locked":0
                },
                {
                    "address":"0x20b9c98d1bbb1f2388720fe9335dbe2a2b4701b1",
                    "tag":"",
                    "is_contract":0,
                    "balance":"203.66596605202",
                    "percent":"0.000172960977869696",
                    "is_locked":0
                },
                {
                    "address":"0xcff219bc4430712e20f9226b4a131d80a0c8d4ca",
                    "tag":"",
                    "is_contract":0,
                    "balance":"61.610039549032",
                    "percent":"0.000052321617075036",
                    "is_locked":0
                },
                {
                    "address":"0x2d3f3416cae1cf7e97825165f01431406cd5e3e7",
                    "tag":"",
                    "is_contract":0,
                    "balance":"56.107899890998",
                    "percent":"0.000047648988289400",
                    "is_locked":0
                },
                {
                    "address":"0x0ed943ce24baebf257488771759f9bf482c39706",
                    "tag":"",
                    "is_contract":1,
                    "balance":"42.17816139722",
                    "percent":"0.000035819318177813",
                    "is_locked":0
                },
                {
                    "address":"0x83ed7463c6f83bb806eb3aaffa6aca11542267d4",
                    "tag":"",
                    "is_contract":0,
                    "balance":"36.23771717451",
                    "percent":"0.000030774464284660",
                    "is_locked":0
                },
                {
                    "address":"0x662d6b152cbe21c72b1eb8f3e51feabfa0165616",
                    "tag":"",
                    "is_contract":0,
                    "balance":"18.574919401172",
                    "percent":"0.000015774536540174",
                    "is_locked":0
                }
            ],
            "lp_total_supply":"1177525.523736662770735191",
            "owner_address":"0x0000000000000000000000000000000000000000",
            "owner_balance":"0",
            "owner_change_balance":"0",
            "owner_percent":"0",
            "personal_slippage_modifiable":"0",
            "selfdestruct":"0",
            "sell_tax":"0.0099997849090013",
            "slippage_modifiable":"0",
            "total_supply":"10240000.000000000000000000",
            "trading_cooldown":"0",
            "transfer_pausable":"0",
            "token_name":"BEE Capital",
            "token_symbol":"BEE"
        }
    }
}